ssh_backchannel/__init__.py
ssh_backchannel/main.py
ssh_backchannel-1.5.0.dist-info/METADATA
ssh_backchannel-1.5.0.dist-info/WHEEL
ssh_backchannel-1.5.0.dist-info/entry_points.txt
ssh_backchannel-1.5.0.dist-info/RECORD
