Metadata-Version: 2.4
Name: ssh-backchannel
Version: 1.5.0
Summary: A Python-based SSH forced-command gatekeeper for remote callbacks.
Author-email: "@readwithai" <talwrii@gmail.com>
License: MIT
Keywords: automation,callback,security,ssh
Classifier: Environment :: Console
Classifier: Programming Language :: Python :: 3
Classifier: Topic :: System :: Networking
Requires-Python: >=3.8
